skill_audio_record/LICENSE
skill_audio_record/LICENSE.md
skill_audio_record/README.md
skill_audio_record/__init__.py
skill_audio_record/skill.json
skill_audio_record/version.py
skill_audio_record/locale/ca-es/Delete.voc
skill_audio_record/locale/ca-es/Play.voc
skill_audio_record/locale/ca-es/PlayRecording.intent
skill_audio_record/locale/ca-es/Recording.voc
skill_audio_record/locale/ca-es/StartRecording.intent
skill_audio_record/locale/ca-es/audio.record.disk.full.dialog
skill_audio_record/locale/ca-es/audio.record.no.recording.dialog
skill_audio_record/locale/ca-es/audio.record.removed.dialog
skill_audio_record/locale/ca-es/audio.record.start.duration.dialog
skill_audio_record/locale/cs-cz/Delete.voc
skill_audio_record/locale/cs-cz/Play.voc
skill_audio_record/locale/cs-cz/PlayRecording.intent
skill_audio_record/locale/cs-cz/Recording.voc
skill_audio_record/locale/cs-cz/StartRecording.intent
skill_audio_record/locale/cs-cz/audio.record.disk.full.dialog
skill_audio_record/locale/cs-cz/audio.record.no.recording.dialog
skill_audio_record/locale/cs-cz/audio.record.removed.dialog
skill_audio_record/locale/cs-cz/audio.record.start.duration.dialog
skill_audio_record/locale/da-dk/Delete.voc
skill_audio_record/locale/da-dk/Play.voc
skill_audio_record/locale/da-dk/PlayRecording.intent
skill_audio_record/locale/da-dk/Recording.voc
skill_audio_record/locale/da-dk/StartRecording.intent
skill_audio_record/locale/da-dk/audio.record.disk.full.dialog
skill_audio_record/locale/da-dk/audio.record.no.recording.dialog
skill_audio_record/locale/da-dk/audio.record.removed.dialog
skill_audio_record/locale/da-dk/audio.record.start.duration.dialog
skill_audio_record/locale/de-de/Delete.voc
skill_audio_record/locale/de-de/Play.voc
skill_audio_record/locale/de-de/PlayRecording.intent
skill_audio_record/locale/de-de/Recording.voc
skill_audio_record/locale/de-de/StartRecording.intent
skill_audio_record/locale/de-de/audio.record.disk.full.dialog
skill_audio_record/neon_skill_audio_record.egg-info/PKG-INFO
skill_audio_record/neon_skill_audio_record.egg-info/SOURCES.txt
skill_audio_record/neon_skill_audio_record.egg-info/dependency_links.txt
skill_audio_record/neon_skill_audio_record.egg-info/entry_points.txt
skill_audio_record/neon_skill_audio_record.egg-info/requires.txt
skill_audio_record/neon_skill_audio_record.egg-info/top_level.txt
neon_skill_audio_record-1.0.1.dist-info/LICENSE
neon_skill_audio_record-1.0.1.dist-info/LICENSE.md
neon_skill_audio_record-1.0.1.dist-info/METADATA
neon_skill_audio_record-1.0.1.dist-info/WHEEL
neon_skill_audio_record-1.0.1.dist-info/entry_points.txt
neon_skill_audio_record-1.0.1.dist-info/top_level.txt
neon_skill_audio_record-1.0.1.dist-info/RECORD
