Metadata-Version: 2.1
Name: neon-skill-audio-record
Version: 1.0.1
Home-page: https://github.com/NeonGeckoCom/skill-audio_record
Author: Neongecko
Author-email: developers@neon.ai
License: BSD-3-Clause
License-File: LICENSE
License-File: LICENSE.md
Requires-Dist: psutil ~=5.6
Requires-Dist: neon-utils ~=1.0
Requires-Dist: ovos-utils >=0.0.28,~=0.0
